curvfaiss/__init__.py
curvfaiss/_swigfaiss.so
curvfaiss/libfaiss.so
curvfaiss/libfaiss_python_callbacks.so
curvfaiss/loader.py
curvfaiss/swigfaiss.py
curvfaiss/contrib/__init__.py
curvfaiss/contrib/client_server.py
curvfaiss/contrib/clustering.py
curvfaiss/contrib/datasets.py
curvfaiss/contrib/evaluation.py
curvfaiss/contrib/exhaustive_search.py
curvfaiss/contrib/factory_tools.py
curvfaiss/contrib/inspect_tools.py
curvfaiss/contrib/ivf_tools.py
curvfaiss/contrib/ondisk.py
curvfaiss/contrib/rpc.py
curvfaiss/contrib/torch_utils.py
curvfaiss/contrib/vecs_io.py
curvfaiss-1.0.0.dist-info/LICENSE
curvfaiss-1.0.0.dist-info/METADATA
curvfaiss-1.0.0.dist-info/WHEEL
curvfaiss-1.0.0.dist-info/top_level.txt
curvfaiss-1.0.0.dist-info/RECORD
